averager/__init__.py
averager/_utils.py
averager/py.typed
averager-3.1.0.dist-info/licenses/LICENSE
averager-3.1.0.dist-info/WHEEL
averager-3.1.0.dist-info/METADATA
averager-3.1.0.dist-info/RECORD
