Metadata-Version: 2.4
Name: averager
Version: 3.1.0
Summary: A simple Python library to calculate averages of values.
Author: Ben Soyka
Author-email: Ben Soyka <hello@bsoyka.me>
License-Expression: MIT
License-File: LICENSE
Classifier: Development Status :: 7 - Inactive
Classifier: Intended Audience :: Developers
Classifier: License :: OSI Approved :: MIT License
Classifier: Natural Language :: English
Classifier: Operating System :: OS Independent
Classifier: Programming Language :: Python
Classifier: Programming Language :: Python :: 3
Classifier: Programming Language :: Python :: 3 :: Only
Classifier: Programming Language :: Python :: 3.9
Classifier: Programming Language :: Python :: 3.10
Classifier: Programming Language :: Python :: 3.11
Classifier: Programming Language :: Python :: 3.12
Classifier: Programming Language :: Python :: 3.13
Classifier: Typing :: Typed
Requires-Dist: deprecated>=1.2.18
Requires-Python: >=3.9
Project-URL: changelog, https://github.com/bsoyka/averager/releases
Project-URL: documentation, https://averager.readthedocs.io
Project-URL: sponsor, https://github.com/sponsors/bsoyka
